commonutil_net_fileservice/__init__.py
commonutil_net_fileservice/config.py
commonutil_net_fileservice/paramikosftp.py
commonutil_net_fileservice/paramikosubexec.py
commonutil_net_fileservice/py.typed
commonutil_net_fileservice/pyftpdlib.py
commonutil_net_fileservice/scp.py
commonutil_net_fileservice-0.1.9.dist-info/METADATA
commonutil_net_fileservice-0.1.9.dist-info/WHEEL
commonutil_net_fileservice-0.1.9.dist-info/top_level.txt
commonutil_net_fileservice-0.1.9.dist-info/RECORD
