Metadata-Version: 2.2
Name: commonutil-net-fileservice
Version: 0.1.9
Summary: Helper routine for file service
Classifier: Development Status :: 5 - Production/Stable
Classifier: Intended Audience :: Developers
Classifier: License :: OSI Approved :: MIT License
Classifier: Operating System :: POSIX
Classifier: Programming Language :: Python :: 3.8
Requires-Python: >=3.8
